README.rst
setup.py
rest_client/__init__.py
rest_client/zerpcap_rest_client.py
rest_zerocap_client.egg-info/PKG-INFO
rest_zerocap_client.egg-info/SOURCES.txt
rest_zerocap_client.egg-info/dependency_links.txt
rest_zerocap_client.egg-info/requires.txt
rest_zerocap_client.egg-info/top_level.txt