Metadata-Version: 2.1
Name: rest-zerocap-client
Version: 0.0.4
Summary: Order Operation
Home-page: 
Author: Tkon
Author-email: 1741226849@qq.com
Platform: all
Classifier: Programming Language :: Python :: 3
Classifier: License :: OSI Approved :: MIT License
Classifier: Operating System :: OS Independent
Requires-Python: >=3.6
